cryspr/__init__.py
cryspr/wyckoffgene.py
cryspr/calculators/__init__.py
cryspr/optimization/__init__.py
cryspr/optimization/global.py
cryspr/optimization/local.py
cryspr/utils/__init__.py
cryspr/utils/analysis.py
cryspr/utils/log.py
cryspr/utils/predict.py
cryspr/utils/struct.py
cryspr-0.0.2.dist-info/LICENSE
cryspr-0.0.2.dist-info/METADATA
cryspr-0.0.2.dist-info/WHEEL
cryspr-0.0.2.dist-info/top_level.txt
cryspr-0.0.2.dist-info/RECORD
