Metadata-Version: 2.1
Name: cryspr
Version: 0.0.2
Summary: Python implementation of crystal structure pre-relaxation and predcition (CrySPR).
Author-email: Wei Nong <nw2y47@outlook.com>, Ruiming Zhu <raymond_zhurm@outlook.com>, Kedar Hippalgaonkar <kedar@ntu.edu.sg>
Maintainer-email: Wei Nong <nw2y47@outlook.com>, Ruiming Zhu <raymond_zhurm@outlook.com>
License: MIT License
Project-URL: Homepage, https://github.com/Tosykie/CrySPR
Project-URL: Issues, https://github.com/Tosykie/CrySPR/issues
Classifier: Programming Language :: Python :: 3
Classifier: Programming Language :: Python :: 3.9
Classifier: Operating System :: OS Independent
Classifier: License :: OSI Approved :: MIT License
Requires-Python: >=3.9
License-File: LICENSE
Requires-Dist: ase
Requires-Dist: pymatgen
Requires-Dist: pyxtal
Requires-Dist: torch
Requires-Dist: matgl
Requires-Dist: chgnet
Requires-Dist: mace-torch
Requires-Dist: scikit-opt
